syclops/__init__.py
syclops/cli.py
syclops/__example_assets__/example_job.syclops.yaml
syclops/__example_assets__/test_job.syclops.yaml
syclops/__example_assets__/example_assets/assets.yaml
syclops/__example_assets__/example_assets/models/iso_object.blend
syclops/__example_assets__/example_assets/models/plants/corn.blend
syclops/__example_assets__/example_assets/models/plants/weeds.blend
syclops/__example_assets__/example_assets/textures/sunflowers_2k.hdr
syclops/__example_assets__/example_assets/textures/brown_mud_dry/brown_mud_dry_diff_1k.jpg
syclops/__example_assets__/example_assets/textures/brown_mud_dry/brown_mud_dry_disp_1k.jpg
syclops/__example_assets__/example_assets/textures/brown_mud_dry/brown_mud_dry_nor_gl_1k.jpg
syclops/__example_assets__/example_assets/textures/brown_mud_dry/brown_mud_dry_rough_1k.jpg
syclops/__example_assets__/example_assets/textures/utility_textures/displacement.png
syclops/__example_assets__/example_assets/textures/utility_textures/perlin.png
syclops/__example_assets__/example_assets/thumbnails/Corn_0.jpg
syclops/__example_assets__/example_assets/thumbnails/Corn_1.jpg
syclops/__example_assets__/example_assets/thumbnails/ISO Object_0.jpg
syclops/__example_assets__/example_assets/thumbnails/Muddy Dry Ground_0.jpg
syclops/__example_assets__/example_assets/thumbnails/Plain Weeds_0.jpg
syclops/__example_assets__/example_assets/thumbnails/Plain Weeds_1.jpg
syclops/__example_assets__/example_assets/thumbnails/Plain Weeds_10.jpg
syclops/__example_assets__/example_assets/thumbnails/Plain Weeds_2.jpg
syclops/__example_assets__/example_assets/thumbnails/Plain Weeds_3.jpg
syclops/__example_assets__/example_assets/thumbnails/Plain Weeds_4.jpg
syclops/__example_assets__/example_assets/thumbnails/Plain Weeds_5.jpg
syclops/__example_assets__/example_assets/thumbnails/Plain Weeds_6.jpg
syclops/__example_assets__/example_assets/thumbnails/Plain Weeds_7.jpg
syclops/__example_assets__/example_assets/thumbnails/Plain Weeds_8.jpg
syclops-1.4.4.dist-info/licenses/LICENSE
syclops-1.4.4.dist-info/METADATA
syclops-1.4.4.dist-info/WHEEL
syclops-1.4.4.dist-info/entry_points.txt
syclops-1.4.4.dist-info/top_level.txt
syclops-1.4.4.dist-info/RECORD
