Metadata-Version: 2.4
Name: syclops
Version: 1.4.4
Summary: Syclops is a Python library for generating synthetic data for machine learning.
Author-email: Anton Elmiger <anton.elmiger@dfki.de>, Kai von Szadkowski <kai.von_szadkowski@dfki.de>
License-Expression: GPL-3.0-or-later
Requires-Python: <3.12,>=3.9
License-File: LICENSE
Requires-Dist: antlr4-python3-runtime==4.8
Requires-Dist: appdirs==1.4.4
Requires-Dist: coacd==1.0.6
Requires-Dist: debugpy==1.6.3
Requires-Dist: filelock==3.9.0
Requires-Dist: GitPython==3.1.29
Requires-Dist: jsonschema==4.17.3
Requires-Dist: opencv-python==4.6.0.66
Requires-Dist: numpy<2.0.0,>=1.23.0
Requires-Dist: Pillow==9.4.0
Requires-Dist: PyYAML==6.0.1
Requires-Dist: requests==2.27.1
Requires-Dist: ruamel.yaml==0.18.10
Requires-Dist: rich==12.6.0
Requires-Dist: wheel==0.38.4
Provides-Extra: dev
Requires-Dist: mkdocs-material==9.4.6; extra == "dev"
Requires-Dist: mkdocs-glightbox==0.1.0; extra == "dev"
Dynamic: license-file
